eli/__init__.py
eli-0.3.1.dist-info/WHEEL
eli-0.3.1.dist-info/METADATA
eli-0.3.1.dist-info/RECORD
