Metadata-Version: 2.1
Name: eli
Version: 0.3.1
Summary: Emacs Lisp runtime interface for Python
Home-page: https://github.com/shawwn/eli
License: MIT
Author: Shawn Presser
Requires-Python: >=3.8,<4.0
Classifier: License :: OSI Approved :: MIT License
Classifier: Programming Language :: Python :: 3
Classifier: Programming Language :: Python :: 3.8
Classifier: Programming Language :: Python :: 3.9
Classifier: Programming Language :: Python :: 3.10
Project-URL: @theshawwn on Twitter, https://www.twitter.com/theshawwn
Project-URL: Shawn Presser's Website, https://www.shawwn.com
Project-URL: Support Shawn Presser on Patreon, https://www.patreon.com/shawwn
Project-URL: sillysaurusx on Hacker News, https://news.ycombinator.com/threads?id=sillysaurusx
